suricata_check/__init__.py
suricata_check/_version.py
suricata_check/suricata_check.py
suricata_check/checkers/__init__.py
suricata_check/checkers/mandatory.py
suricata_check/checkers/community/__init__.py
suricata_check/checkers/community/best.py
suricata_check/checkers/community/unexpected.py
suricata_check/checkers/interface/__init__.py
suricata_check/checkers/interface/checker.py
suricata_check/checkers/interface/dummy.py
suricata_check/checkers/principle/__init__.py
suricata_check/checkers/principle/_utils.py
suricata_check/checkers/principle/ml.py
suricata_check/checkers/principle/principle.py
suricata_check/checkers/styleguide/__init__.py
suricata_check/checkers/styleguide/metadata.py
suricata_check/checkers/styleguide/msg.py
suricata_check/checkers/styleguide/order.py
suricata_check/checkers/styleguide/overall.py
suricata_check/checkers/styleguide/pcre.py
suricata_check/checkers/styleguide/performance.py
suricata_check/checkers/styleguide/reference.py
suricata_check/checkers/styleguide/sid.py
suricata_check/checkers/styleguide/state.py
suricata_check/checkers/styleguide/whitespace.py
suricata_check/data/principle_ml_checker.pkl
suricata_check/tests/__init__.py
suricata_check/tests/checker.py
suricata_check/utils/__init__.py
suricata_check/utils/_click.py
suricata_check/utils/_path.py
suricata_check/utils/checker.py
suricata_check/utils/checker_typing.py
suricata_check/utils/regex.py
suricata_check-0.0.1.dist-info/LICENSE
suricata_check-0.0.1.dist-info/METADATA
suricata_check-0.0.1.dist-info/WHEEL
suricata_check-0.0.1.dist-info/entry_points.txt
suricata_check-0.0.1.dist-info/top_level.txt
suricata_check-0.0.1.dist-info/RECORD
