Metadata-Version: 2.2
Name: suricata-check
Version: 0.0.1
Summary: A command line utility to provide feedback on Suricata rules.
Author: Koen Teuwen
License:                       EUROPEAN UNION PUBLIC LICENCE v. 1.2
Project-URL: homepage, https://github.com/Koen1999/suricata-check
Project-URL: repository, https://github.com/Koen1999/suricata-check
Project-URL: documentation, https://github.com/Koen1999/suricata-check/README.md
Project-URL: bugtracker, https://github.com/Koen1999/suricata-check/issues
Keywords: suricata,cli,rule,rules,check,checker,feedback,network intrusion detection
Classifier: Development Status :: 4 - Beta
Classifier: Intended Audience :: Science/Research
Classifier: Intended Audience :: Education
Classifier: Intended Audience :: Developers
Classifier: Intended Audience :: Information Technology
Classifier: Natural Language :: English
Classifier: Environment :: Console
Classifier: Topic :: Scientific/Engineering
Classifier: Topic :: Security
Classifier: Topic :: Software Development
Classifier: Topic :: Software Development :: Quality Assurance
Classifier: Topic :: Education
Classifier: Topic :: Education :: Computer Aided Instruction (CAI)
Classifier: Topic :: Utilities
Classifier: Topic :: File Formats
Classifier: Programming Language :: Python :: 3
Classifier: Programming Language :: Python :: 3.9
Classifier: Programming Language :: Python :: 3.10
Classifier: Programming Language :: Python :: 3.11
Classifier: Programming Language :: Python :: 3.12
Classifier: Programming Language :: Python :: 3.13
Classifier: Programming Language :: Python :: 3 :: Only
Classifier: Operating System :: OS Independent
Classifier: Operating System :: POSIX
Classifier: Operating System :: Microsoft :: Windows
Classifier: Operating System :: MacOS
Classifier: Framework :: Pytest
Classifier: License :: OSI Approved :: European Union Public Licence 1.2 (EUPL 1.2)
Requires-Python: >=3.9
License-File: LICENSE
Requires-Dist: click>=8.1.7
Requires-Dist: idstools>=0.6.5
Requires-Dist: tabulate>=0.9.0
Provides-Extra: performance
Requires-Dist: regex>=2024.5.15; extra == "performance"
Provides-Extra: ml
Requires-Dist: numpy>=1.26.4; extra == "ml"
Requires-Dist: pandas>=2.0.3; extra == "ml"
Requires-Dist: scikit-learn==1.5.1; extra == "ml"
Requires-Dist: xgboost==2.0.3; extra == "ml"
Provides-Extra: dev
Requires-Dist: pytest>=8.2.1; extra == "dev"
Requires-Dist: pytest-cov>=5.0.0; extra == "dev"
Requires-Dist: flake8>=7.1.0; extra == "dev"
Requires-Dist: ruff>=0.4.9; extra == "dev"
Requires-Dist: black>=24.4.2; extra == "dev"
Requires-Dist: pyright>=1.1.367; extra == "dev"
Requires-Dist: sphinx>=7.3.7; extra == "dev"
Requires-Dist: sphinx-rtd-theme>=2.0.0; extra == "dev"
Requires-Dist: myst-parser[linkify]>=3.0.1; extra == "dev"
Requires-Dist: sphinx-click>=6.0.0; extra == "dev"
Requires-Dist: sphinx-autoapi>=3.4.0; extra == "dev"
